LICENSE
README.md
setup.cfg
setup.py
milinamaso/__init__.py
milinamaso/version.py
milinamaso.egg-info/PKG-INFO
milinamaso.egg-info/SOURCES.txt
milinamaso.egg-info/dependency_links.txt
milinamaso.egg-info/requires.txt
milinamaso.egg-info/top_level.txt
milinamaso.egg-info/zip-safe
milinamaso/trainer/__init__.py
milinamaso/trainer/core.py
milinamaso/trainer/utils.py